freqit/__init__.py
freqit/oneway.py
freqit-1.0.dist-info/METADATA
freqit-1.0.dist-info/WHEEL
freqit-1.0.dist-info/licenses/LICENSE.md
freqit-1.0.dist-info/RECORD
