Metadata-Version: 2.1
Name: freqit
Version: 1.0
Summary: Better frequency and crosstab tables.
Project-URL: Homepage, https://github.com/la-mcnamara/freqit
Project-URL: Bug Tracker, https://github.com/la-mcnamara/freqit/issues
Author-email: Lauren McNamara <lauren.mcnamara@gmail.com>
License-File: LICENSE.md
Classifier: License :: OSI Approved :: MIT License
Classifier: Operating System :: OS Independent
Classifier: Programming Language :: Python :: 3
Requires-Python: >=3.8
Requires-Dist: pandas
